plcx/__init__.py
plcx/constants.py
plcx/exceptions.py
plcx/bag/__init__.py
plcx/bag/pack.py
plcx/bag/reader.py
plcx/bag/unpack.py
plcx/bag/writer.py
plcx/comm/__init__.py
plcx/comm/client.py
plcx/comm/server.py
plcx/tests/__init__.py
plcx/utils/__init__.py
plcx/utils/boolean.py
plcx/utils/coroutine.py
plcx/utils/find.py
plcx-0.9.2.dist-info/LICENSE
plcx-0.9.2.dist-info/METADATA
plcx-0.9.2.dist-info/WHEEL
plcx-0.9.2.dist-info/top_level.txt
plcx-0.9.2.dist-info/RECORD
