Metadata-Version: 2.1
Name: plcx
Version: 0.9.2
Summary: async PLC communication
Home-page: https://github.com/Cognexa/plcx
Author: Cognexa Solutions s.r.o.
Author-email: info@cognexa.com
License: MIT
Keywords: async plc
Platform: UNKNOWN
Classifier: Development Status :: 4 - Beta
Classifier: Intended Audience :: Developers
Classifier: Operating System :: Unix
Classifier: License :: OSI Approved :: MIT License
Classifier: Programming Language :: Python :: 3.7
Requires-Dist: atomicwrites (>=1.1)
Requires-Dist: attrs (>=17.1)
Requires-Dist: importlib-metadata (>=0.18)
Requires-Dist: more-itertools (>=7)
Requires-Dist: pluggy (>=0.11)
Requires-Dist: py (>=1.10)
Requires-Dist: pyparsing (>=2.2)
Requires-Dist: pytest (>=4)
Requires-Dist: python-forge (>=18)
Requires-Dist: six (>=1.9)
Requires-Dist: wcwidth (>=0.1)
Requires-Dist: zipp (>=0.5)
